README.md
setup.py
gsenha/__init__.py
gsenha/exceptions.py
gsenha/manager.py
gsenha.egg-info/PKG-INFO
gsenha.egg-info/SOURCES.txt
gsenha.egg-info/dependency_links.txt
gsenha.egg-info/requires.txt
gsenha.egg-info/top_level.txt
tests/__init__.py
tests/test_password_manager.py