Metadata-Version: 1.0
Name: gsenha
Version: 0.0.11
Summary: client for gsenha api
Home-page: UNKNOWN
Author: Big Data
Author-email: bigdata@corp.globo.com
License: MIT
Platform: UNKNOWN
